ludo_query/__init__.py
ludo_query-0.1.0.dist-info/METADATA
ludo_query-0.1.0.dist-info/WHEEL
ludo_query-0.1.0.dist-info/RECORD
