Metadata-Version: 2.4
Name: ludo-query
Version: 0.1.0
Summary: A chatbot guide to help users understand accesibility tools used in game development.
Requires-Python: >=3.12
Requires-Dist: svlearn-bootcamp>=0.1.7
